python_boilerplate_decaf/__init__.py
python_boilerplate_decaf/python_boilerplate_decaf.py
python_boilerplate_decaf-0.2.0.dist-info/DESCRIPTION.rst
python_boilerplate_decaf-0.2.0.dist-info/METADATA
python_boilerplate_decaf-0.2.0.dist-info/RECORD
python_boilerplate_decaf-0.2.0.dist-info/WHEEL
python_boilerplate_decaf-0.2.0.dist-info/metadata.json
python_boilerplate_decaf-0.2.0.dist-info/top_level.txt
