Metadata-Version: 2.0
Name: python-boilerplate-decaf
Version: 0.2.0
Summary: Python Boilerplate CfB contains all the boilerplate you need to create a Python package within the DeCaF project
Home-page: https://github.com/hredestig/python_boilerplate_decaf
Author: Henning Redestig
Author-email: henred@dtu.dk
License: GNU General Public License v3
Keywords: python_boilerplate_decaf
Platform: UNKNOWN
Classifier: Development Status :: 2 - Pre-Alpha
Classifier: Intended Audience :: Developers
Classifier: Natural Language :: English
Classifier: Programming Language :: Python :: 2
Classifier: Programming Language :: Python :: 2.7
Classifier: Programming Language :: Python :: 3
Classifier: Programming Language :: Python :: 3.4
Classifier: Programming Language :: Python :: 3.5
